[
    {
        "name": "Uwezo Academy",
        "stack": {
            "name": "Angular",
            "iconClasses": "fab fa-angular"
        },
        "description": "An education app project from GADS2021 community project",
        "sourceUrl": "https://github.com/Susan56789/Uwezo-Academy",
        "previewUrl": "https://uwezo-academu.herokuapp.com/",
        "featured": true
    },
    {
        "name": "Facebook Clone",
        "stack": {
            "name": "React",
            "iconClasses": "fab fa-react"
        },
        "description": "Facebook clone app , sign in with google authentication",
        "sourceUrl": "https://github.com/Susan56789/Facebook-Clone",
        "previewUrl": "https://facebook-clone-jade-beta.vercel.app/",
        "featured": true
    },
    {
        "name": "Recipe App",
        "stack": {
            "name": "React",
            "iconClasses": "fab fa-react"
        },
        "description": "Recipe app made with react. Fetch recipe data from REST API",
        "sourceUrl": "https://github.com/Susan56789/Recipes-101",
        "previewUrl": "https://recipe-101.vercel.app/",
        "featured": true
    },
    {
        "name": "Tour App",
        "stack": {
            "name": "React",
            "iconClasses": "fab fa-react"
        },
        "description": "App to display various tour locations in Kenya",
        "sourceUrl": "https://github.com/Susan56789/omna-tours",
        "previewUrl": "https://omna-tours.netlify.app/",
        "featured": true
    }
]